black_nbconvert.py
black_nbconvert-0.4.0.dist-info/LICENSE
black_nbconvert-0.4.0.dist-info/METADATA
black_nbconvert-0.4.0.dist-info/WHEEL
black_nbconvert-0.4.0.dist-info/entry_points.txt
black_nbconvert-0.4.0.dist-info/top_level.txt
black_nbconvert-0.4.0.dist-info/RECORD
