Metadata-Version: 2.1
Name: black-nbconvert
Version: 0.4.0
Summary: Apply black to ipynb files
Home-page: https://github.com/dfm/black_nbconvert
Author: Dan Foreman-Mackey
Author-email: foreman.mackey@gmail.com
License: MIT
Platform: UNKNOWN
Classifier: Development Status :: 4 - Beta
Classifier: Environment :: Console
Classifier: Intended Audience :: Developers
Classifier: License :: OSI Approved :: MIT License
Classifier: Operating System :: OS Independent
Classifier: Programming Language :: Python
Classifier: Programming Language :: Python :: 3.6
Classifier: Programming Language :: Python :: 3.7
Classifier: Programming Language :: Python :: 3 :: Only
Classifier: Topic :: Software Development :: Libraries :: Python Modules
Classifier: Topic :: Software Development :: Quality Assurance
Requires-Python: >=3.6
License-File: LICENSE
Requires-Dist: black
Requires-Dist: nbconvert
